pyphashml/__init__.py
pyphashml/imgclient.py
pyphashml/imgcmp.py
pyphashml/phashml.py
pyphashml/resources/__init__.py
pyphashml/resources/mobilenetv2_deepaec_1792to256_combined.pb
pyphashml-0.1.0.dist-info/LICENSE
pyphashml-0.1.0.dist-info/METADATA
pyphashml-0.1.0.dist-info/WHEEL
pyphashml-0.1.0.dist-info/top_level.txt
pyphashml-0.1.0.dist-info/RECORD
