Metadata-Version: 2.1
Name: pyphashml
Version: 0.1.0
Summary: pHashML Image Perceptual Hash
Home-page: https://github.com/starkdg/pyphashml
Author: DGStarkweather
Author-email: starkdg@gmx.com
License: UNKNOWN
Project-URL: Bug Tracker, https://github.com/starkdg/pyphashml/issues
Platform: UNKNOWN
Classifier: Programming Language :: Python :: 3
Classifier: License :: OSI Approved :: Apache Software License
Classifier: Operating System :: OS Independent
Classifier: Topic :: Scientific/Engineering :: Image Recognition
Classifier: Intended Audience :: Information Technology
Classifier: Intended Audience :: Developers
Requires-Python: >=3.7
License-File: LICENSE
Requires-Dist: bitstring (>=3)
Requires-Dist: numpy (>=1.19)
Requires-Dist: tensorflow (<2,>=1.14)
Requires-Dist: redis (>=3)
